[
  {
    "id": "may",
    "isActive": true,
    "currentMatchId": "match-1cqblh8",
    "miniTimerText": "Match starts in",
    "qualifyingResults": {
      "part-04xspbq": {
        "wins": 2,
        "losses": 1,
        "winsByKO": 1,
        "winsByJD": 1,
        "winsByNS": 0,
        "lossesByKO": 1,
        "lossesByJD": 0,
        "lossesByNS": 0,
        "opponentIds": [
          "0a41c0a",
          "rot076r",
          "part-fdrxhj5"
        ],
        "opponentWins": 5,
        "score": 2.09905
      },
      "part-aw653qy": {
        "wins": 1,
        "losses": 2,
        "winsByKO": 1,
        "winsByJD": 0,
        "winsByNS": 0,
        "lossesByKO": 1,
        "lossesByJD": 1,
        "lossesByNS": 0,
        "opponentIds": [
          "8pii4jf",
          "uvy1k73",
          "part-y3konnp"
        ],
        "opponentWins": 5,
        "score": 1.09895
      },
      "part-hh5ch23": {
        "wins": 3,
        "losses": 0,
        "winsByKO": 2,
        "winsByJD": 1,
        "winsByNS": 0,
        "lossesByKO": 0,
        "lossesByJD": 0,
        "lossesByNS": 0,
        "opponentIds": [
          "part-qpm0bjg",
          "part-fdrxhj5",
          "uvy1k73"
        ],
        "opponentWins": 5,
        "score": 3.20005
      },
      "part-fdrxhj5": {
        "wins": 1,
        "losses": 2,
        "winsByKO": 0,
        "winsByJD": 1,
        "winsByNS": 0,
        "lossesByKO": 2,
        "lossesByJD": 0,
        "lossesByNS": 0,
        "opponentIds": [
          "part-dx6qvml",
          "part-hh5ch23",
          "part-04xspbq"
        ],
        "opponentWins": 5,
        "score": 0.99805
      },
      "part-ul19jgv": {
        "wins": 0,
        "losses": 0,
        "winsByKO": 0,
        "winsByJD": 0,
        "winsByNS": 0,
        "lossesByKO": 0,
        "lossesByJD": 0,
        "lossesByNS": 0,
        "opponentIds": [],
        "opponentWins": 0,
        "score": 0
      },
      "part-qpm0bjg": {
        "wins": 2,
        "losses": 1,
        "winsByKO": 2,
        "winsByJD": 0,
        "winsByNS": 0,
        "lossesByKO": 0,
        "lossesByJD": 1,
        "lossesByNS": 0,
        "opponentIds": [
          "part-hh5ch23",
          "part-odwrzot",
          "3osxali"
        ],
        "opponentWins": 4,
        "score": 2.19994
      },
      "part-rzeus3u": {
        "wins": 0,
        "losses": 0,
        "winsByKO": 0,
        "winsByJD": 0,
        "winsByNS": 0,
        "lossesByKO": 0,
        "lossesByJD": 0,
        "lossesByNS": 0,
        "opponentIds": [],
        "opponentWins": 0,
        "score": 0
      },
      "part-dllub2q": {
        "wins": 2,
        "losses": 1,
        "winsByKO": 2,
        "winsByJD": 0,
        "winsByNS": 0,
        "lossesByKO": 0,
        "lossesByJD": 1,
        "lossesByNS": 0,
        "opponentIds": [
          "puvpwxl",
          "0a41c0a",
          "rot076r"
        ],
        "opponentWins": 6,
        "score": 2.19996
      },
      "part-uov2lni": {
        "wins": 1,
        "losses": 2,
        "winsByKO": 0,
        "winsByJD": 1,
        "winsByNS": 0,
        "lossesByKO": 2,
        "lossesByJD": 0,
        "lossesByNS": 0,
        "opponentIds": [
          "3osxali",
          "puvpwxl",
          "part-dx6qvml"
        ],
        "opponentWins": 3,
        "score": 0.99803
      },
      "part-odwrzot": {
        "wins": 0,
        "losses": 3,
        "winsByKO": 0,
        "winsByJD": 0,
        "winsByNS": 0,
        "lossesByKO": 2,
        "lossesByJD": 1,
        "lossesByNS": 0,
        "opponentIds": [
          "rot076r",
          "part-qpm0bjg",
          "luecccm"
        ],
        "opponentWins": 4,
        "score": -0.00206
      },
      "part-y3konnp": {
        "wins": 2,
        "losses": 1,
        "winsByKO": 2,
        "winsByJD": 0,
        "winsByNS": 0,
        "lossesByKO": 1,
        "lossesByJD": 0,
        "lossesByNS": 0,
        "opponentIds": [
          "uvy1k73",
          "luecccm",
          "part-aw653qy"
        ],
        "opponentWins": 4,
        "score": 2.19904
      },
      "part-fok7byp": {
        "wins": 0,
        "losses": 0,
        "winsByKO": 0,
        "winsByJD": 0,
        "winsByNS": 0,
        "lossesByKO": 0,
        "lossesByJD": 0,
        "lossesByNS": 0,
        "opponentIds": [],
        "opponentWins": 0,
        "score": 0
      },
      "part-dx6qvml": {
        "wins": 0,
        "losses": 3,
        "winsByKO": 0,
        "winsByJD": 0,
        "winsByNS": 0,
        "lossesByKO": 1,
        "lossesByJD": 2,
        "lossesByNS": 0,
        "opponentIds": [
          "part-fdrxhj5",
          "8pii4jf",
          "part-uov2lni"
        ],
        "opponentWins": 3,
        "score": -0.00117
      },
      "uhunewo": {
        "wins": 0,
        "losses": 0,
        "winsByKO": 0,
        "winsByJD": 0,
        "winsByNS": 0,
        "lossesByKO": 0,
        "lossesByJD": 0,
        "lossesByNS": 0,
        "opponentIds": [],
        "opponentWins": 0,
        "score": 0
      },
      "rot076r": {
        "wins": 1,
        "losses": 2,
        "winsByKO": 0,
        "winsByJD": 1,
        "winsByNS": 0,
        "lossesByKO": 1,
        "lossesByJD": 1,
        "lossesByNS": 0,
        "opponentIds": [
          "part-odwrzot",
          "part-04xspbq",
          "part-dllub2q"
        ],
        "opponentWins": 4,
        "score": 0.99894
      },
      "luecccm": {
        "wins": 1,
        "losses": 2,
        "winsByKO": 1,
        "winsByJD": 0,
        "winsByNS": 0,
        "lossesByKO": 2,
        "lossesByJD": 0,
        "lossesByNS": 0,
        "opponentIds": [
          "hfk4hiu",
          "part-y3konnp",
          "part-odwrzot"
        ],
        "opponentWins": 4,
        "score": 1.09804
      },
      "0a41c0a": {
        "wins": 3,
        "losses": 0,
        "winsByKO": 1,
        "winsByJD": 2,
        "winsByNS": 0,
        "lossesByKO": 0,
        "lossesByJD": 0,
        "lossesByNS": 0,
        "opponentIds": [
          "part-04xspbq",
          "part-dllub2q",
          "hfk4hiu"
        ],
        "opponentWins": 6,
        "score": 3.10006
      },
      "hfk4hiu": {
        "wins": 2,
        "losses": 1,
        "winsByKO": 2,
        "winsByJD": 0,
        "winsByNS": 0,
        "lossesByKO": 0,
        "lossesByJD": 1,
        "lossesByNS": 0,
        "opponentIds": [
          "luecccm",
          "3osxali",
          "0a41c0a"
        ],
        "opponentWins": 5,
        "score": 2.19995
      },
      "3osxali": {
        "wins": 1,
        "losses": 2,
        "winsByKO": 1,
        "winsByJD": 0,
        "winsByNS": 0,
        "lossesByKO": 2,
        "lossesByJD": 0,
        "lossesByNS": 0,
        "opponentIds": [
          "part-uov2lni",
          "hfk4hiu",
          "part-qpm0bjg"
        ],
        "opponentWins": 5,
        "score": 1.09805
      },
      "8pii4jf": {
        "wins": 1,
        "losses": 2,
        "winsByKO": 1,
        "winsByJD": 0,
        "winsByNS": 0,
        "lossesByKO": 2,
        "lossesByJD": 0,
        "lossesByNS": 0,
        "opponentIds": [
          "part-aw653qy",
          "part-dx6qvml",
          "puvpwxl"
        ],
        "opponentWins": 3,
        "score": 1.09803
      },
      "uvy1k73": {
        "wins": 2,
        "losses": 1,
        "winsByKO": 1,
        "winsByJD": 1,
        "winsByNS": 0,
        "lossesByKO": 1,
        "lossesByJD": 0,
        "lossesByNS": 0,
        "opponentIds": [
          "part-y3konnp",
          "part-aw653qy",
          "part-hh5ch23"
        ],
        "opponentWins": 6,
        "score": 2.09906
      },
      "kf92kfb": {
        "wins": 0,
        "losses": 0,
        "winsByKO": 0,
        "winsByJD": 0,
        "winsByNS": 0,
        "lossesByKO": 0,
        "lossesByJD": 0,
        "lossesByNS": 0,
        "opponentIds": [],
        "opponentWins": 0,
        "score": 0
      },
      "puvpwxl": {
        "wins": 2,
        "losses": 1,
        "winsByKO": 2,
        "winsByJD": 0,
        "winsByNS": 0,
        "lossesByKO": 1,
        "lossesByJD": 0,
        "lossesByNS": 0,
        "opponentIds": [
          "part-dllub2q",
          "part-uov2lni",
          "8pii4jf"
        ],
        "opponentWins": 4,
        "score": 2.19904
      }
    },
    "qualifyingRankings": [
      {
        "id": "part-hh5ch23",
        "position": 1
      },
      {
        "id": "0a41c0a",
        "position": 2
      },
      {
        "id": "part-dllub2q",
        "position": 3
      },
      {
        "id": "part-qpm0bjg",
        "position": 4
      },
      {
        "id": "part-y3konnp",
        "position": 5
      },
      {
        "id": "puvpwxl",
        "position": 6
      },
      {
        "id": "uvy1k73",
        "position": 7
      },
      {
        "id": "part-04xspbq",
        "position": 8
      },
      {
        "id": "part-aw653qy",
        "position": 9
      },
      {
        "id": "3osxali",
        "position": 10
      },
      {
        "id": "luecccm",
        "position": 11
      },
      {
        "id": "8pii4jf",
        "position": 12
      },
      {
        "id": "rot076r",
        "position": 13
      },
      {
        "id": "part-fdrxhj5",
        "position": 14
      },
      {
        "id": "part-uov2lni",
        "position": 15
      },
      {
        "id": "part-ul19jgv",
        "position": 16
      },
      {
        "id": "part-rzeus3u",
        "position": 17
      },
      {
        "id": "part-fok7byp",
        "position": 18
      },
      {
        "id": "uhunewo",
        "position": 19
      },
      {
        "id": "kf92kfb",
        "position": 20
      },
      {
        "id": "part-dx6qvml",
        "position": 21
      },
      {
        "id": "part-odwrzot",
        "position": 22
      },
      {
        "id": "hfk4hiu",
        "position": 23
      }
    ],
    "brackets": [
      {
        "name": "Championship",
        "size": 8
      },
      {
        "name": "9th Place",
        "size": 8
      }
    ],
    "finalRankings": [
      {
        "id": "part-qpm0bjg",
        "position": 1
      },
      {
        "id": "0a41c0a",
        "position": 2
      },
      {
        "id": "part-y3konnp",
        "position": 3
      },
      {
        "id": "part-04xspbq",
        "position": 4
      },
      {
        "id": "part-hh5ch23",
        "position": 5
      },
      {
        "id": "part-dllub2q",
        "position": 6
      },
      {
        "id": "puvpwxl",
        "position": 7
      },
      {
        "id": "uvy1k73",
        "position": 8
      },
      {
        "id": "part-aw653qy",
        "position": 9
      },
      {
        "id": "part-uov2lni",
        "position": 10
      },
      {
        "id": "part-fdrxhj5",
        "position": 11
      },
      {
        "id": "rot076r",
        "position": 12
      },
      {
        "id": "3osxali",
        "position": 13
      },
      {
        "id": "luecccm",
        "position": 14
      },
      {
        "id": "8pii4jf",
        "position": 15
      },
      {
        "id": "part-odwrzot",
        "position": 16
      },
      {
        "id": "part-dx6qvml",
        "position": 17
      },
      {
        "id": "hfk4hiu",
        "position": 18
      }
    ]
  }
]